aerocloud/__init__.py
aerocloud/environment.py
aerocloud/packages.py
aerocloud-0.0.3.dist-info/LICENSE
aerocloud-0.0.3.dist-info/METADATA
aerocloud-0.0.3.dist-info/WHEEL
aerocloud-0.0.3.dist-info/top_level.txt
aerocloud-0.0.3.dist-info/RECORD
