Metadata-Version: 2.1
Name: aerocloud
Version: 0.0.3
Summary: Aerocloud Python client
Home-page: https://github.com/Aerometrex/aerocloud-python-client.git
Author: Aerometrex Ltd
Author-email: tyson.jones@aerometrex.com.au
License: UNKNOWN
Platform: UNKNOWN
Classifier: Programming Language :: Python :: 3
Classifier: License :: OSI Approved :: MIT License
Classifier: Operating System :: OS Independent
Requires-Python: >=3.6
License-File: LICENSE
